uniqcharcounter/__init__.py
uniqcharcounter/app/__init__.py
uniqcharcounter/app/app.py
uniqcharcounter/utils/__init__.py
uniqcharcounter/utils/exceptions.py
uniqcharcounter/utils/functions.py
uniqcharcounter-1.0.dist-info/LICENSE
uniqcharcounter-1.0.dist-info/METADATA
uniqcharcounter-1.0.dist-info/WHEEL
uniqcharcounter-1.0.dist-info/entry_points.txt
uniqcharcounter-1.0.dist-info/top_level.txt
uniqcharcounter-1.0.dist-info/RECORD
