Metadata-Version: 2.1
Name: uniqcharcounter
Version: 1.0
Summary: Calculate count of uniq chars in string or file
Home-page: UNKNOWN
Author: Dihtiar Vadym
License: UNKNOWN
Platform: UNKNOWN
Requires-Python: >=3.8
License-File: LICENSE
